minimocas/__init__.py
minimocas/minimocas.py
minimocas-1.0.1.dist-info/LICENSE
minimocas-1.0.1.dist-info/METADATA
minimocas-1.0.1.dist-info/WHEEL
minimocas-1.0.1.dist-info/top_level.txt
minimocas-1.0.1.dist-info/RECORD
