Metadata-Version: 2.1
Name: minimocas
Version: 1.0.1
Summary: minimocas companion package
Author-email: Roman <author@example.com>
License: MIT
Classifier: Programming Language :: Python :: 3
Classifier: Operating System :: OS Independent
Requires-Python: >=3.8
License-File: LICENSE
